xrayphasemap/__init__.py
xrayphasemap/analysis.py
xrayphasemap/map.py
xrayphasemap/phase.py
xrayphasemap/test_analysis.py
xrayphasemap/test_map.py
xrayphasemap/test_phase.py
xrayphasemap/tests.py
xrayphasemap-0.3.1.dist-info/DESCRIPTION.rst
xrayphasemap-0.3.1.dist-info/METADATA
xrayphasemap-0.3.1.dist-info/RECORD
xrayphasemap-0.3.1.dist-info/WHEEL
xrayphasemap-0.3.1.dist-info/metadata.json
xrayphasemap-0.3.1.dist-info/top_level.txt
