Metadata-Version: 2.0
Name: xrayphasemap
Version: 0.3.1
Summary: Create phase map from x-ray elemental maps.
Home-page: https://github.com/drix00/xrayphasemap
Author: Hendrix Demers
Author-email: hendrix.demers@mail.mcgill.ca
License: Apache Software License 2.0
Keywords: xrayphasemap
Platform: UNKNOWN
Classifier: Development Status :: 5 - Production/Stable
Classifier: Environment :: Console
Classifier: Intended Audience :: Developers
Classifier: Intended Audience :: Science/Research
Classifier: License :: OSI Approved :: Apache Software License
Classifier: Natural Language :: English
Classifier: Programming Language :: Python
Classifier: Operating System :: OS Independent
Classifier: Topic :: Scientific/Engineering
Requires-Dist: Pillow
Requires-Dist: numpy
Requires-Dist: scipy
Requires-Dist: h5py
Requires-Dist: matplotlib
